freezing/__init__.py
freezing/__version__.py
freezing/freezeindex.py
freezing/test/__init__.py
freezing/test/testFreezeindex.py
freeze_index-1.0.0.dist-info/METADATA
freeze_index-1.0.0.dist-info/WHEEL
freeze_index-1.0.0.dist-info/licenses/LICENSE
freeze_index-1.0.0.dist-info/RECORD
