Metadata-Version: 2.4
Name: freeze-index
Version: 1.0.0
Summary: Unified freezing of gait index computation
Project-URL: Documentation, https://github.com/magnesag/freeze-index
Project-URL: Issues, https://github.com/magnesag/freeze-index/issues
Project-URL: Source, https://github.com/magnesag/freeze-index
Author: Henrik Maurenbrecher, Carlo Mangiante, Roman Sobkuliak
Author-email: Alessandro Schaer <aschaer@magnes.ch>
License-Expression: BSD-3-Clause
License-File: LICENSE
Keywords: Parkinson's disease,freeze index,freezing of gait,gait analysis
Classifier: Programming Language :: Python :: 3.10
Classifier: Programming Language :: Python :: 3.11
Classifier: Programming Language :: Python :: 3.12
Classifier: Programming Language :: Python :: 3.13
Requires-Python: >=3.10
Requires-Dist: matplotlib>=3.10.3
Requires-Dist: numpy>=2.2.5
Requires-Dist: scikit-learn>=1.6.1
Requires-Dist: scipy>=1.15.3
